{
  "placeholderImages": [
    {
      "id": "blog-1",
      "description": "Abstract architecture",
      "imageUrl": "https://picsum.photos/seed/blog1/1200/800",
      "imageHint": "abstract architecture"
    },
    {
      "id": "blog-2",
      "description": "Minimalist desk setup",
      "imageUrl": "https://picsum.photos/seed/blog2/1200/800",
      "imageHint": "minimalist desk"
    },
    {
      "id": "blog-3",
      "description": "Cityscape at night",
      "imageUrl": "https://picsum.photos/seed/blog3/1200/800",
      "imageHint": "city night"
    },
    {
      "id": "blog-4",
      "description": "Forest path in autumn",
      "imageUrl": "https://picsum.photos/seed/blog4/1200/800",
      "imageHint": "forest path"
    },
    {
      "id": "blog-5",
      "description": "Person coding on a laptop",
      "imageUrl": "https://picsum.photos/seed/blog5/1200/800",
      "imageHint": "laptop code"
    },
    {
      "id": "blog-6",
      "description": "Coffee cup on a wooden table",
      "imageUrl": "https://picsum.photos/seed/blog6/1200/800",
      "imageHint": "coffee wood"
    },
    {
      "id": "blog-7",
      "description": "Mountain range with a clear sky",
      "imageUrl": "https://picsum.photos/seed/blog7/1200/800",
      "imageHint": "mountains sky"
    },
    {
      "id": "blog-8",
      "description": "Vintage camera on a map",
      "imageUrl": "https://picsum.photos/seed/blog8/1200/800",
      "imageHint": "vintage camera"
    },
    {
      "id": "user-1",
      "description": "Profile picture of Alex",
      "imageUrl": "https://picsum.photos/seed/user1/200/200",
      "imageHint": "person portrait"
    },
    {
      "id": "user-2",
      "description": "Profile picture of Maria",
      "imageUrl": "https://picsum.photos/seed/user2/200/200",
      "imageHint": "woman smiling"
    },
    {
      "id": "user-3",
      "description": "Profile picture of Chen",
      "imageUrl": "https://picsum.photos/seed/user3/200/200",
      "imageHint": "man glasses"
    },
    {
      "id": "user-4",
      "description": "Profile picture of Sam",
      "imageUrl": "https://picsum.photos/seed/user4/200/200",
      "imageHint": "person profile"
    },
    {
      "id": "user-5",
      "description": "Profile picture of a team member",
      "imageUrl": "https://picsum.photos/seed/team1/400/400",
      "imageHint": "professional headshot"
    },
    {
      "id": "user-6",
      "description": "Profile picture of a team member",
      "imageUrl": "https://picsum.photos/seed/team2/400/400",
      "imageHint": "business portrait"
    },
    {
      "id": "user-7",
      "description": "Profile picture of a team member",
      "imageUrl": "https://picsum.photos/seed/team3/400/400",
      "imageHint": "creative professional"
    }
  ]
}